README.md
setup.py
dataforseo_client/__init__.py
dataforseo_client/api_client.py
dataforseo_client/api_response.py
dataforseo_client/configuration.py
dataforseo_client/exceptions.py
dataforseo_client/rest.py
dataforseo_client.egg-info/PKG-INFO
dataforseo_client.egg-info/SOURCES.txt
dataforseo_client.egg-info/dependency_links.txt
dataforseo_client.egg-info/requires.txt
dataforseo_client.egg-info/top_level.txt
dataforseo_client/api/__init__.py
dataforseo_client/api/ai_optimization_api.py
dataforseo_client/api/app_data_api.py
dataforseo_client/api/appendix_api.py
dataforseo_client/api/backlinks_api.py
dataforseo_client/api/business_data_api.py
dataforseo_client/api/content_analysis_api.py
dataforseo_client/api/content_generation_api.py
dataforseo_client/api/dataforseo_labs_api.py
dataforseo_client/api/domain_analytics_api.py
dataforseo_client/api/keywords_data_api.py
dataforseo_client/api/merchant_api.py
dataforseo_client/api/on_page_api.py
dataforseo_client/api/serp_api.py
dataforseo_client/models/__init__.py
dataforseo_client/models/about_this_result_element.py
dataforseo_client/models/absolute_items.py
dataforseo_client/models/ad_link_element.py
dataforseo_client/models/address_info.py
dataforseo_client/models/ads_search.py
dataforseo_client/models/advertiser.py
dataforseo_client/models/ai_mode_ai_overview_expanded_component_info.py
dataforseo_client/models/ai_mode_ai_overview_info.py
dataforseo_client/models/ai_mode_ai_overview_reference_info.py
dataforseo_client/models/ai_mode_ai_overview_shopping_element_info.py
dataforseo_client/models/ai_mode_images_element_info.py
dataforseo_client/models/ai_mode_link_element_info.py
dataforseo_client/models/ai_mode_rectangle_info.py
dataforseo_client/models/ai_mode_table_info.py
dataforseo_client/models/ai_monthly_searches.py
dataforseo_client/models/ai_optimization_ai_keyword_data_available_filters_response_info.py
dataforseo_client/models/ai_optimization_ai_keyword_data_available_filters_result_info.py
dataforseo_client/models/ai_optimization_ai_keyword_data_available_filters_task_info.py
dataforseo_client/models/ai_optimization_ai_keyword_data_keywords_search_volume_live_item.py
