Metadata-Version: 2.4
Name: dataforseo-client
Version: 2.0.18
Summary: DataForSEO API documentation
Home-page: https://github.com/dataforseo/PythonClient
Author: DataForSeo
Author-email: info@dataforseo.com
Keywords: OpenAPI,DataForSEO,DataForSEO API documentation
Requires-Dist: urllib3>=1.25.3
Requires-Dist: python-dateutil
Requires-Dist: pydantic>=2
Requires-Dist: typing-extensions>=4.7.1
Dynamic: author
Dynamic: author-email
Dynamic: description
Dynamic: description-content-type
Dynamic: home-page
Dynamic: keywords
Dynamic: requires-dist
Dynamic: summary
